{
  "venues": [
    {
      "name": "Sofitel London Heathrow",
      "postcode": "",
      "group": "Terminal 5",
      "fhrsid": 519347,
      "matchedName": "Sofitel London Heathrow",
      "matchedPostcode": "TW6 2GD",
      "status": "ok",
      "note": "locked to supplied FHRSID",
      "candidates": []
    },
    {
      "name": "Thistle London Heathrow T5",
      "postcode": "",
      "group": "Terminal 5",
      "fhrsid": 519844,
      "matchedName": "Thistle London Heathrow Hotel",
      "matchedPostcode": "UB7 0EQ",
      "status": "ok",
      "note": "locked to supplied FHRSID",
      "candidates": []
    },
    {
      "name": "Premier Inn London Heathrow T5",
      "postcode": "",
      "group": "Terminal 5",
      "fhrsid": 519281,
      "matchedName": "Premier Inn T5",
      "matchedPostcode": "UB7 0EA",
      "status": "ok",
      "note": "locked to supplied FHRSID",
      "candidates": []
    },
    {
      "name": "Sheraton Heathrow Hotel",
      "postcode": "",
      "group": "Bath Road",
      "fhrsid": 519852,
      "matchedName": "Sheraton Heathrow Hotel",
      "matchedPostcode": "UB7 0HJ",
      "status": "ok",
      "note": "locked to supplied FHRSID",
      "candidates": []
    },
    {
      "name": "Hyatt Place London Heathrow",
      "postcode": "",
      "group": "Bath Road",
      "fhrsid": 519306,
      "matchedName": "Hyatt Place London Heathrow",
      "matchedPostcode": "UB7 0DG",
      "status": "ok",
      "note": "locked to supplied FHRSID",
      "candidates": []
    },
    {
      "name": "Staybridge Suites / Holiday Inn Bath Road",
      "postcode": "",
      "group": "Bath Road",
      "fhrsid": 1095940,
      "matchedName": "Trading as Staybridge Suites / Holiday Inn Heathrow",
      "matchedPostcode": "UB7 0DQ",
      "status": "ok",
      "note": "locked to supplied FHRSID",
      "candidates": []
    },
    {
      "name": "Leonardo Hotel London Heathrow",
      "postcode": "",
      "group": "Bath Road",
      "fhrsid": 519301,
      "matchedName": "Leonardo Hotel",
      "matchedPostcode": "UB7 0DP",
      "status": "ok",
      "note": "locked to supplied FHRSID",
      "candidates": []
    },
    {
      "name": "Radisson RED London Heathrow",
      "postcode": "",
      "group": "Bath Road",
      "fhrsid": 518684,
      "matchedName": "Radisson Red Hotel",
      "matchedPostcode": "UB7 0DU",
      "status": "ok",
      "note": "locked to supplied FHRSID",
      "candidates": []
    },
    {
      "name": "Aerotel London Heathrow",
      "postcode": "",
      "group": "Central",
      "fhrsid": 1661140,
      "matchedName": "Aerotel London (landside)",
      "matchedPostcode": "TW6 1AA",
      "status": "ok",
      "note": "locked to supplied FHRSID",
      "candidates": []
    },
    {
      "name": "ibis Styles London Heathrow",
      "postcode": "",
      "group": "Bath Road",
      "fhrsid": 910259,
      "matchedName": "Ibis Style Hotel",
      "matchedPostcode": "UB3 5BX",
      "status": "ok",
      "note": "locked to supplied FHRSID",
      "candidates": []
    },
    {
      "name": "Renaissance London Heathrow",
      "postcode": "",
      "group": "Bath Road",
      "fhrsid": 520204,
      "matchedName": "Renaissance London Heathrow Hotel",
      "matchedPostcode": "TW6 2AQ",
      "status": "ok",
      "note": "locked to supplied FHRSID",
      "candidates": []
    },
    {
      "name": "Radisson Blu Edwardian Heathrow",
      "postcode": "",
      "group": "Bath Road",
      "fhrsid": 1742446,
      "matchedName": "Radisson Blu London Heathrow",
      "matchedPostcode": "UB3 5AW",
      "status": "ok",
      "note": "locked to supplied FHRSID",
      "candidates": []
    },
    {
      "name": "London Heathrow Marriott",
      "postcode": "",
      "group": "Bath Road",
      "fhrsid": 1836231,
      "matchedName": "London Heathrow Marriott Hotel",
      "matchedPostcode": "UB3 5AN",
      "status": "ok",
      "note": "locked to supplied FHRSID",
      "candidates": []
    },
    {
      "name": "Sheraton Skyline Hotel",
      "postcode": "",
      "group": "Bath Road",
      "fhrsid": 520206,
      "matchedName": "Sheraton Skyline Hotel",
      "matchedPostcode": "UB3 5BP",
      "status": "ok",
      "note": "locked to supplied FHRSID",
      "candidates": []
    },
    {
      "name": "Best Western Heathrow Ariel",
      "postcode": "",
      "group": "Bath Road",
      "fhrsid": 1354702,
      "matchedName": "Best Western London Ariel Hotel",
      "matchedPostcode": "UB3 5AJ",
      "status": "ok",
      "note": "locked to supplied FHRSID",
      "candidates": []
    },
    {
      "name": "ibis London Heathrow",
      "postcode": "",
      "group": "Bath Road",
      "fhrsid": 657530,
      "matchedName": "Ibis London Heathrow",
      "matchedPostcode": "UB3 5AL",
      "status": "ok",
      "note": "locked to supplied FHRSID",
      "candidates": []
    },
    {
      "name": "Premier Inn London Heathrow T2/T3",
      "postcode": "",
      "group": "Bath Road",
      "fhrsid": 519050,
      "matchedName": "Premier Inn",
      "matchedPostcode": "TW6 2AB",
      "status": "ok",
      "note": "locked to supplied FHRSID",
      "candidates": []
    },
    {
      "name": "Moxy London Heathrow",
      "postcode": "",
      "group": "Cranford",
      "fhrsid": 1466590,
      "matchedName": "Moxy Hotel - London Heathrow Airport",
      "matchedPostcode": "TW5 9UH",
      "status": "ok",
      "note": "locked to supplied FHRSID",
      "candidates": []
    },
    {
      "name": "ibis budget London Heathrow Central",
      "postcode": "",
      "group": "Cranford",
      "fhrsid": 490443,
      "matchedName": "Ibis",
      "matchedPostcode": "TW5 9TW",
      "status": "ok",
      "note": "locked to supplied FHRSID",
      "candidates": []
    },
    {
      "name": "Atrium Hotel Heathrow",
      "postcode": "",
      "group": "Hatton Cross",
      "fhrsid": 1501854,
      "matchedName": "Atrium Hotel Heathrow",
      "matchedPostcode": "TW14 0AW",
      "status": "ok",
      "note": "locked to supplied FHRSID",
      "candidates": []
    },
    {
      "name": "Premier Inn London Heathrow T4",
      "postcode": "",
      "group": "Terminal 4",
      "fhrsid": 1000595,
      "matchedName": "Premier Inn",
      "matchedPostcode": "TW6 3FH",
      "status": "ok",
      "note": "locked to supplied FHRSID",
      "candidates": []
    },
    {
      "name": "Hilton London Heathrow T4",
      "postcode": "",
      "group": "Terminal 4",
      "fhrsid": 520094,
      "matchedName": "Hilton Hotel - Terminal 4",
      "matchedPostcode": "TW6 3AF",
      "status": "ok",
      "note": "locked to supplied FHRSID",
      "candidates": []
    },
    {
      "name": "Crowne Plaza / Holiday Inn Express T4",
      "postcode": "",
      "group": "Terminal 4",
      "fhrsid": 1207522,
      "matchedName": "Crowne Plaza / Holiday Inn Express T4",
      "matchedPostcode": "TW6 3FJ",
      "status": "ok",
      "note": "locked to supplied FHRSID",
      "candidates": []
    },
    {
      "name": "Hilton London Heathrow T5",
      "postcode": "",
      "group": "Colnbrook / M4",
      "fhrsid": 1683444,
      "matchedName": "Hilton London Heathrow Airport Terminal 5",
      "matchedPostcode": "SL3 0FF",
      "status": "ok",
      "note": "locked to supplied FHRSID",
      "candidates": []
    },
    {
      "name": "Premier Inn London Heathrow M4 J4",
      "postcode": "",
      "group": "M4 J4",
      "fhrsid": 518938,
      "matchedName": "Premier Inn",
      "matchedPostcode": "UB3 1RW",
      "status": "ok",
      "note": "locked to supplied FHRSID",
      "candidates": []
    },
    {
      "name": "The Globe Pub & Kitchen",
      "postcode": "TW6 2GA",
      "group": "Eatery",
      "fhrsid": 1486351,
      "matchedName": "The Globe (Landside departure level T5)",
      "matchedPostcode": "TW6 2GA",
      "status": "ok",
      "note": "locked to supplied FHRSID",
      "candidates": []
    },
    {
      "name": "Kaniz Indian",
      "postcode": "UB7 0DE",
      "group": "Eatery",
      "fhrsid": 1453394,
      "matchedName": "Kaniz Restaurant-Heathrow",
      "matchedPostcode": "UB7 0DE",
      "status": "ok",
      "note": "locked to supplied FHRSID",
      "candidates": []
    },
    {
      "name": "Achari Indian Restaurant",
      "postcode": "UB7 0HU",
      "group": "Eatery",
      "fhrsid": 1641951,
      "matchedName": "Achari",
      "matchedPostcode": "UB7 0HU",
      "status": "ok",
      "note": "locked to supplied FHRSID",
      "candidates": []
    },
    {
      "name": "McDonald’s",
      "postcode": "UB7 0EA",
      "group": "Eatery",
      "fhrsid": 1536935,
      "matchedName": "McDonalds",
      "matchedPostcode": "UB7 0EA",
      "status": "ok",
      "note": "locked to supplied FHRSID",
      "candidates": []
    },
    {
      "name": "The Three Magpies",
      "postcode": "TW6 2AU",
      "group": "Eatery",
      "fhrsid": 520146,
      "matchedName": "The Three Magpies",
      "matchedPostcode": "TW6 2AU",
      "status": "ok",
      "note": "locked to supplied FHRSID",
      "candidates": []
    },
    {
      "name": "Ostrich Inn",
      "postcode": "SL3 0JZ",
      "group": "Eatery",
      "fhrsid": 816858,
      "matchedName": "The Ostrich",
      "matchedPostcode": "SL3 0JZ",
      "status": "ok",
      "note": "locked to supplied FHRSID",
      "candidates": []
    },
    {
      "name": "The Pheasant Inn",
      "postcode": "UB3 5LX",
      "group": "Eatery",
      "fhrsid": 520243,
      "matchedName": "The Pheasant PH",
      "matchedPostcode": "UB3 5LX",
      "status": "ok",
      "note": "locked to supplied FHRSID",
      "candidates": []
    },
    {
      "name": "New Bettola",
      "postcode": "SL3 0NZ",
      "group": "Eatery",
      "fhrsid": 1804535,
      "matchedName": "New Bettola",
      "matchedPostcode": "SL3 0NZ",
      "status": "ok",
      "note": "locked to supplied FHRSID",
      "candidates": []
    },
    {
      "name": "The White Horse",
      "postcode": "UB7 0EE",
      "group": "Eatery",
      "fhrsid": 519822,
      "matchedName": "White Horse Inn",
      "matchedPostcode": "UB7 0EE",
      "status": "ok",
      "note": "locked to supplied FHRSID",
      "candidates": []
    },
    {
      "name": "BJ’s Sandwich Bar",
      "postcode": "UB7 0DE",
      "group": "Eatery",
      "fhrsid": 519994,
      "matchedName": "B J Sandwich Bar",
      "matchedPostcode": "UB7 0DE",
      "status": "ok",
      "note": "locked to supplied FHRSID",
      "candidates": []
    },
    {
      "name": "Istanbul Grill",
      "postcode": "UB7 0DE",
      "group": "Eatery",
      "fhrsid": 997111,
      "matchedName": "Istanbul Grill, Fish and Chips",
      "matchedPostcode": "UB7 0DE",
      "status": "ok",
      "note": "locked to supplied FHRSID",
      "candidates": []
    }
  ]
}